setup.py
example_client/__init__.py
example_client.egg-info/PKG-INFO
example_client.egg-info/SOURCES.txt
example_client.egg-info/dependency_links.txt
example_client.egg-info/requires.txt
example_client.egg-info/top_level.txt